{
  "type": "GROUP",
"name": "All Requests",
"path": "",
"pathFormatted": "group_missing-name-b06d1",
"stats": {
    "name": "All Requests",
    "numberOfRequests": {
        "total": 416,
        "ok": 294,
        "ko": 122
    },
    "minResponseTime": {
        "total": 161,
        "ok": 161,
        "ko": 1828
    },
    "maxResponseTime": {
        "total": 16032,
        "ok": 16032,
        "ko": 15398
    },
    "meanResponseTime": {
        "total": 6019,
        "ok": 4635,
        "ko": 9352
    },
    "standardDeviation": {
        "total": 4254,
        "ok": 3675,
        "ko": 3667
    },
    "percentiles1": {
        "total": 4403,
        "ok": 3797,
        "ko": 9852
    },
    "percentiles2": {
        "total": 9220,
        "ok": 5250,
        "ko": 12046
    },
    "percentiles3": {
        "total": 15154,
        "ok": 12852,
        "ko": 15307
    },
    "percentiles4": {
        "total": 15405,
        "ok": 15476,
        "ko": 15339
    },
    "group1": {
    "name": "t < 800 ms",
    "htmlName": "t < 800 ms",
    "count": 17,
    "percentage": 4
},
    "group2": {
    "name": "800 ms <= t < 1200 ms",
    "htmlName": "t >= 800 ms <br> t < 1200 ms",
    "count": 13,
    "percentage": 3
},
    "group3": {
    "name": "t >= 1200 ms",
    "htmlName": "t >= 1200 ms",
    "count": 264,
    "percentage": 63
},
    "group4": {
    "name": "failed",
    "htmlName": "failed",
    "count": 122,
    "percentage": 29
},
    "meanNumberOfRequestsPerSecond": {
        "total": 15.407407407407407,
        "ok": 10.88888888888889,
        "ko": 4.518518518518518
    }
},
"contents": {
"req_mongodb---save-5c0eb": {
        "type": "REQUEST",
        "name": "MongoDB - Save",
"path": "MongoDB - Save",
"pathFormatted": "req_mongodb---save-5c0eb",
"stats": {
    "name": "MongoDB - Save",
    "numberOfRequests": {
        "total": 104,
        "ok": 104,
        "ko": 0
    },
    "minResponseTime": {
        "total": 161,
        "ok": 161,
        "ko": 0
    },
    "maxResponseTime": {
        "total": 4456,
        "ok": 4456,
        "ko": 0
    },
    "meanResponseTime": {
        "total": 2226,
        "ok": 2226,
        "ko": 0
    },
    "standardDeviation": {
        "total": 1167,
        "ok": 1167,
        "ko": 0
    },
    "percentiles1": {
        "total": 2270,
        "ok": 2270,
        "ko": 0
    },
    "percentiles2": {
        "total": 3094,
        "ok": 3094,
        "ko": 0
    },
    "percentiles3": {
        "total": 4218,
        "ok": 4218,
        "ko": 0
    },
    "percentiles4": {
        "total": 4345,
        "ok": 4345,
        "ko": 0
    },
    "group1": {
    "name": "t < 800 ms",
    "htmlName": "t < 800 ms",
    "count": 13,
    "percentage": 13
},
    "group2": {
    "name": "800 ms <= t < 1200 ms",
    "htmlName": "t >= 800 ms <br> t < 1200 ms",
    "count": 10,
    "percentage": 10
},
    "group3": {
    "name": "t >= 1200 ms",
    "htmlName": "t >= 1200 ms",
    "count": 81,
    "percentage": 78
},
    "group4": {
    "name": "failed",
    "htmlName": "failed",
    "count": 0,
    "percentage": 0
},
    "meanNumberOfRequestsPerSecond": {
        "total": 3.8518518518518516,
        "ok": 3.8518518518518516,
        "ko": 0
    }
}
    },"req_mysql---load-068dd": {
        "type": "REQUEST",
        "name": "MySql - Load",
"path": "MySql - Load",
"pathFormatted": "req_mysql---load-068dd",
"stats": {
    "name": "MySql - Load",
    "numberOfRequests": {
        "total": 104,
        "ok": 5,
        "ko": 99
    },
    "minResponseTime": {
        "total": 332,
        "ok": 332,
        "ko": 2251
    },
    "maxResponseTime": {
        "total": 15398,
        "ok": 7796,
        "ko": 15398
    },
    "meanResponseTime": {
        "total": 9996,
        "ok": 5440,
        "ko": 10226
    },
    "standardDeviation": {
        "total": 3497,
        "ok": 2617,
        "ko": 3377
    },
    "percentiles1": {
        "total": 10550,
        "ok": 6456,
        "ko": 10965
    },
    "percentiles2": {
        "total": 12257,
        "ok": 6465,
        "ko": 12327
    },
    "percentiles3": {
        "total": 15315,
        "ok": 7530,
        "ko": 15316
    },
    "percentiles4": {
        "total": 15340,
        "ok": 7743,
        "ko": 15341
    },
    "group1": {
    "name": "t < 800 ms",
    "htmlName": "t < 800 ms",
    "count": 1,
    "percentage": 1
},
    "group2": {
    "name": "800 ms <= t < 1200 ms",
    "htmlName": "t >= 800 ms <br> t < 1200 ms",
    "count": 0,
    "percentage": 0
},
    "group3": {
    "name": "t >= 1200 ms",
    "htmlName": "t >= 1200 ms",
    "count": 4,
    "percentage": 4
},
    "group4": {
    "name": "failed",
    "htmlName": "failed",
    "count": 99,
    "percentage": 95
},
    "meanNumberOfRequestsPerSecond": {
        "total": 3.8518518518518516,
        "ok": 0.18518518518518517,
        "ko": 3.6666666666666665
    }
}
    },"req_mysql---save-7eab2": {
        "type": "REQUEST",
        "name": "MySql - Save",
"path": "MySql - Save",
"pathFormatted": "req_mysql---save-7eab2",
"stats": {
    "name": "MySql - Save",
    "numberOfRequests": {
        "total": 104,
        "ok": 82,
        "ko": 22
    },
    "minResponseTime": {
        "total": 757,
        "ok": 757,
        "ko": 3390
    },
    "maxResponseTime": {
        "total": 16032,
        "ok": 16032,
        "ko": 7723
    },
    "meanResponseTime": {
        "total": 8185,
        "ok": 8836,
        "ko": 5759
    },
    "standardDeviation": {
        "total": 4087,
        "ok": 4245,
        "ko": 2082
    },
    "percentiles1": {
        "total": 7697,
        "ok": 8590,
        "ko": 7543
    },
    "percentiles2": {
        "total": 11085,
        "ok": 11928,
        "ko": 7675
    },
    "percentiles3": {
        "total": 15303,
        "ok": 15401,
        "ko": 7705
    },
    "percentiles4": {
        "total": 15978,
        "ok": 15992,
        "ko": 7719
    },
    "group1": {
    "name": "t < 800 ms",
    "htmlName": "t < 800 ms",
    "count": 1,
    "percentage": 1
},
    "group2": {
    "name": "800 ms <= t < 1200 ms",
    "htmlName": "t >= 800 ms <br> t < 1200 ms",
    "count": 3,
    "percentage": 3
},
    "group3": {
    "name": "t >= 1200 ms",
    "htmlName": "t >= 1200 ms",
    "count": 78,
    "percentage": 75
},
    "group4": {
    "name": "failed",
    "htmlName": "failed",
    "count": 22,
    "percentage": 21
},
    "meanNumberOfRequestsPerSecond": {
        "total": 3.8518518518518516,
        "ok": 3.037037037037037,
        "ko": 0.8148148148148148
    }
}
    },"req_mongodb---load-1e535": {
        "type": "REQUEST",
        "name": "MongoDB - Load",
"path": "MongoDB - Load",
"pathFormatted": "req_mongodb---load-1e535",
"stats": {
    "name": "MongoDB - Load",
    "numberOfRequests": {
        "total": 104,
        "ok": 103,
        "ko": 1
    },
    "minResponseTime": {
        "total": 174,
        "ok": 174,
        "ko": 1828
    },
    "maxResponseTime": {
        "total": 7490,
        "ok": 7490,
        "ko": 1828
    },
    "meanResponseTime": {
        "total": 3667,
        "ok": 3685,
        "ko": 1828
    },
    "standardDeviation": {
        "total": 1288,
        "ok": 1282,
        "ko": 0
    },
    "percentiles1": {
        "total": 3857,
        "ok": 3867,
        "ko": 1828
    },
    "percentiles2": {
        "total": 4432,
        "ok": 4433,
        "ko": 1828
    },
    "percentiles3": {
        "total": 4823,
        "ok": 4823,
        "ko": 1828
    },
    "percentiles4": {
        "total": 7475,
        "ok": 7476,
        "ko": 1828
    },
    "group1": {
    "name": "t < 800 ms",
    "htmlName": "t < 800 ms",
    "count": 2,
    "percentage": 2
},
    "group2": {
    "name": "800 ms <= t < 1200 ms",
    "htmlName": "t >= 800 ms <br> t < 1200 ms",
    "count": 0,
    "percentage": 0
},
    "group3": {
    "name": "t >= 1200 ms",
    "htmlName": "t >= 1200 ms",
    "count": 101,
    "percentage": 97
},
    "group4": {
    "name": "failed",
    "htmlName": "failed",
    "count": 1,
    "percentage": 1
},
    "meanNumberOfRequestsPerSecond": {
        "total": 3.8518518518518516,
        "ok": 3.814814814814815,
        "ko": 0.037037037037037035
    }
}
    }
}

}